unicode_string_contain_check/__init__.py
unicode_string_contain_check/utf_iostream.py
unicode_string_contain_check-2.0.0.dist-info/LICENSE
unicode_string_contain_check-2.0.0.dist-info/METADATA
unicode_string_contain_check-2.0.0.dist-info/WHEEL
unicode_string_contain_check-2.0.0.dist-info/top_level.txt
unicode_string_contain_check-2.0.0.dist-info/RECORD
