Metadata-Version: 2.1
Name: unicode-string-contain-check
Version: 2.0.0
Summary: String contain validation for non-Latin language system
Home-page: https://github.com/rk0cc/unicode-string-contain-check
Author: rk0cc
Author-email: cyruschan1212@gmail.com
License: Apache
Platform: UNKNOWN
Classifier: Programming Language :: Python :: 3
Classifier: License :: OSI Approved :: Apache Software License
Classifier: Operating System :: OS Independent
Classifier: Topic :: Text Processing :: Filters
Requires-Python: >=3.8
